easydiffraction/__init__.py
easydiffraction/__main__.py
easydiffraction/analysis/__init__.py
easydiffraction/analysis/analysis.py
easydiffraction/analysis/fitting.py
easydiffraction/analysis/calculators/__init__.py
easydiffraction/analysis/calculators/base.py
easydiffraction/analysis/calculators/crysfml.py
easydiffraction/analysis/calculators/cryspy.py
easydiffraction/analysis/calculators/factory.py
easydiffraction/analysis/calculators/pdffit.py
easydiffraction/analysis/categories/__init__.py
easydiffraction/analysis/categories/aliases.py
easydiffraction/analysis/categories/constraints.py
easydiffraction/analysis/categories/joint_fit_experiments.py
easydiffraction/analysis/fit_helpers/__init__.py
easydiffraction/analysis/fit_helpers/metrics.py
easydiffraction/analysis/fit_helpers/reporting.py
easydiffraction/analysis/fit_helpers/tracking.py
easydiffraction/analysis/minimizers/__init__.py
easydiffraction/analysis/minimizers/base.py
easydiffraction/analysis/minimizers/dfols.py
easydiffraction/analysis/minimizers/factory.py
easydiffraction/analysis/minimizers/lmfit.py
easydiffraction/core/__init__.py
easydiffraction/core/category.py
easydiffraction/core/collection.py
easydiffraction/core/datablock.py
easydiffraction/core/diagnostic.py
easydiffraction/core/factory.py
easydiffraction/core/guard.py
easydiffraction/core/identity.py
easydiffraction/core/parameters.py
easydiffraction/core/singletons.py
easydiffraction/core/validation.py
easydiffraction/crystallography/__init__.py
easydiffraction/crystallography/crystallography.py
easydiffraction/crystallography/space_groups.pkl.gz
easydiffraction/crystallography/space_groups.py
easydiffraction/display/__init__.py
easydiffraction/display/base.py
easydiffraction/display/plotting.py
easydiffraction/display/tables.py
easydiffraction/display/utils.py
easydiffraction/display/plotters/__init__.py
easydiffraction/display/plotters/ascii.py
easydiffraction/display/plotters/base.py
easydiffraction/display/plotters/plotly.py
easydiffraction-0.10.1.dist-info/METADATA
easydiffraction-0.10.1.dist-info/WHEEL
easydiffraction-0.10.1.dist-info/licenses/LICENSE
easydiffraction-0.10.1.dist-info/RECORD
