Metadata-Version: 2.4
Name: easydiffraction
Version: 0.10.1
Summary: Diffraction data analysis
Project-URL: homepage, https://easydiffraction.org
Project-URL: documentation, https://docs.easydiffraction.org/lib
Project-URL: source, https://github.com/easyscience/diffraction-lib
Project-URL: tracker, https://github.com/easyscience/diffraction-lib/issues
Author: EasyDiffraction contributors
License: BSD 3-Clause License
License-File: LICENSE
Classifier: Intended Audience :: Science/Research
Classifier: License :: OSI Approved :: BSD License
Classifier: Operating System :: OS Independent
Classifier: Programming Language :: Python :: 3
Classifier: Programming Language :: Python :: 3 :: Only
Classifier: Programming Language :: Python :: 3.11
Classifier: Programming Language :: Python :: 3.12
Classifier: Programming Language :: Python :: 3.13
Classifier: Topic :: Scientific/Engineering
Requires-Python: <3.14,>=3.11
Requires-Dist: asciichartpy
Requires-Dist: asteval
Requires-Dist: bumps
Requires-Dist: colorama
Requires-Dist: cryspy
Requires-Dist: dfo-ls
Requires-Dist: diffpy-pdffit2
Requires-Dist: diffpy-utils
Requires-Dist: gemmi
Requires-Dist: lmfit
Requires-Dist: numpy
Requires-Dist: pooch
Requires-Dist: rich
Requires-Dist: scipy
Requires-Dist: sympy
Requires-Dist: tabulate
Requires-Dist: typeguard
Requires-Dist: typer
Requires-Dist: uncertainties
Requires-Dist: varname
Provides-Extra: all
Requires-Dist: build; extra == 'all'
Requires-Dist: darkdetect; extra == 'all'
Requires-Dist: docformatter; extra == 'all'
Requires-Dist: interrogate; extra == 'all'
Requires-Dist: jinja2; extra == 'all'
Requires-Dist: jupyterquiz; extra == 'all'
Requires-Dist: jupytext; extra == 'all'
Requires-Dist: mike; extra == 'all'
Requires-Dist: mkdocs; extra == 'all'
Requires-Dist: mkdocs-autorefs; extra == 'all'
Requires-Dist: mkdocs-jupyter; extra == 'all'
Requires-Dist: mkdocs-markdownextradata-plugin; extra == 'all'
Requires-Dist: mkdocs-material; extra == 'all'
Requires-Dist: mkdocs-plugin-inline-svg; extra == 'all'
Requires-Dist: mkdocstrings-python; extra == 'all'
Requires-Dist: nbmake; extra == 'all'
Requires-Dist: nbqa; extra == 'all'
Requires-Dist: nbstripout; extra == 'all'
Requires-Dist: pandas; extra == 'all'
Requires-Dist: plotly; extra == 'all'
Requires-Dist: pre-commit; extra == 'all'
Requires-Dist: py3dmol; extra == 'all'
Requires-Dist: pytest; extra == 'all'
Requires-Dist: pytest-cov; extra == 'all'
Requires-Dist: pytest-xdist; extra == 'all'
Requires-Dist: pyyaml; extra == 'all'
Requires-Dist: radon; extra == 'all'
Requires-Dist: ruff; extra == 'all'
Requires-Dist: validate-pyproject[all]; extra == 'all'
Requires-Dist: versioningit; extra == 'all'
Provides-Extra: dev
Requires-Dist: build; extra == 'dev'
Requires-Dist: docformatter; extra == 'dev'
Requires-Dist: interrogate; extra == 'dev'
Requires-Dist: jinja2; extra == 'dev'
Requires-Dist: jupyterquiz; extra == 'dev'
Requires-Dist: jupytext; extra == 'dev'
Requires-Dist: nbmake; extra == 'dev'
Requires-Dist: nbqa; extra == 'dev'
Requires-Dist: nbstripout; extra == 'dev'
Requires-Dist: pre-commit; extra == 'dev'
Requires-Dist: pytest; extra == 'dev'
Requires-Dist: pytest-cov; extra == 'dev'
Requires-Dist: pytest-xdist; extra == 'dev'
Requires-Dist: radon; extra == 'dev'
Requires-Dist: ruff; extra == 'dev'
Requires-Dist: validate-pyproject[all]; extra == 'dev'
Requires-Dist: versioningit; extra == 'dev'
Provides-Extra: docs
Requires-Dist: mike; extra == 'docs'
Requires-Dist: mkdocs; extra == 'docs'
Requires-Dist: mkdocs-autorefs; extra == 'docs'
Requires-Dist: mkdocs-jupyter; extra == 'docs'
Requires-Dist: mkdocs-markdownextradata-plugin; extra == 'docs'
Requires-Dist: mkdocs-material; extra == 'docs'
Requires-Dist: mkdocs-plugin-inline-svg; extra == 'docs'
Requires-Dist: mkdocstrings-python; extra == 'docs'
Requires-Dist: pyyaml; extra == 'docs'
Provides-Extra: visualization
Requires-Dist: darkdetect; extra == 'visualization'
Requires-Dist: pandas; extra == 'visualization'
Requires-Dist: plotly; extra == 'visualization'
Requires-Dist: py3dmol; extra == 'visualization'
